vastcap/__init__.py
vastcap/client.py
vastcap/exceptions.py
vastcap/types.py
vastcap-1.0.1.dist-info/licenses/LICENSE
vastcap-1.0.1.dist-info/METADATA
vastcap-1.0.1.dist-info/WHEEL
vastcap-1.0.1.dist-info/top_level.txt
vastcap-1.0.1.dist-info/RECORD
