Metadata-Version: 2.4
Name: vastcap
Version: 1.0.1
Summary: VastCap Python SDK
Home-page: https://github.com/vastien/vastcap-python
Author: vastien
Author-email: contact@vast.sh
License: MIT
Classifier: Programming Language :: Python :: 3
Classifier: License :: OSI Approved :: MIT License
Classifier: Operating System :: OS Independent
Requires-Python: >=3.11
License-File: LICENSE
Dynamic: author
Dynamic: author-email
Dynamic: classifier
Dynamic: description
Dynamic: description-content-type
Dynamic: home-page
Dynamic: license
Dynamic: license-file
Dynamic: requires-python
Dynamic: summary
